osxdocker/__init__.py
osxdocker/docker_logs.py
osxdocker/utils/__init__.py
osxdocker/utils/docker_base.py
osxdocker/utils/warn.py
osxdocker-0.1.3.dist-info/entry_points.txt
osxdocker-0.1.3.dist-info/LICENSE
osxdocker-0.1.3.dist-info/WHEEL
osxdocker-0.1.3.dist-info/METADATA
osxdocker-0.1.3.dist-info/RECORD
